NeuraForge/__init__.py
NeuraForge/main.py
NeuraForge-0.3.0.dist-info/METADATA
NeuraForge-0.3.0.dist-info/WHEEL
NeuraForge-0.3.0.dist-info/top_level.txt
NeuraForge-0.3.0.dist-info/RECORD
