Metadata-Version: 2.1
Name: NeuraForge
Version: 0.3.0
Summary: A basic AI library built off of google gemini api
Author: Aaroh Charne
Author-email: aaroh.charne@gmail.com
Classifier: Programming Language :: Python :: 3
Classifier: License :: OSI Approved :: MIT License
Classifier: Operating System :: OS Independent
Classifier: Development Status :: 3 - Alpha
Classifier: Intended Audience :: Developers
Classifier: Natural Language :: English
Classifier: Topic :: Software Development :: Libraries :: Python Modules
Requires-Python: >=3.9
Requires-Dist: google.generativeai
